{
    "other": "metadata",
    "provenance": {
        "agent": {
            "dep:503a7b959f91ac691a0881ee724635427ea5f3862aa105040e30a0fee50cc1a00": {
                "prov:type": {
                    "$": "ocn:ethereum-account",
                    "type": "xsd:string"
                }
            }
        },
        "wasGeneratedBy": {
            "_:wGB4": {
                "prov:entity": "dep:this",
                "prov:activity": "dep:112593b6-2120-49e9-b357-0d610a4119ea"
            }
        },
        "activity": {
            "dep:112593b6-2120-49e9-b357-0d610a4119ea": {
                "prov:type": {
                    "$": "ocn:publish",
                    "type": "xsd:string"
                },
                "prov:endTime": "2019-05-22T10:28:30.834+08:00"
            }
        },
        "prefix": {
            "xsd": "http://www.w3.org/2001/XMLSchema#",
            "prov": "http://www.w3.org/ns/prov#",
            "dep": "http://datacraft.sg/schemas"
        },
        "wasAssociatedWith": {
            "_:wAW4": {
                "prov:agent": "dep:503a7b959f91ac691a0881ee724635427ea5f3862aa105040e30a0fee50cc1a00",
                "prov:activity": "dep:112593b6-2120-49e9-b357-0d610a4119ea"
            }
        },
        "entity": {
            "dep:this": {
                "prov:type": {
                    "$": "ocn:asset",
                    "type": "xsd:string"
                }
            }
        }
    }
}
